{
  "recommendations": [
    {
      "id": 1,
      "name": "Brooklyn Steel",
      "borough": "Brooklyn",
      "area": "East Williamsburg",
      "category": "🎶",
      "url": "https://www.bowerypresents.com/venues/brooklyn-steel",
      "img": "https://i0.wp.com/livemusicblog.com/wp-content/uploads/2018/06/DSC2272.jpg?resize=1068%2C674&ssl=1",
      "description": "This is a super cool, standing-room-only venue with great sound!",
      "user": "Leah",
      "likes": 3
    },
    {
      "name": "Caffè Vita",
      "borough": "Brooklyn",
      "area": "Bushwick",
      "category": "☕️",
      "url": "https://www.caffevita.com/pages/locations#new_york",
      "img": "https://foodcurated.com/wp-content/uploads/2018/01/vita-6.jpg",
      "description": "Hands down best coffee in Bushwick. Try the lavender latte or campfire latte!",
      "likes": 6,
      "user": "Leah",
      "id": 2
    },
    {
      "name": "Evil Katsu",
      "borough": "Manhattan",
      "area": "East Village",
      "category": "🌭",
      "url": "https://www.evilkatsu.com/",
      "img": "https://infatuation.imgix.net/media/images/reviews/evil-katsu/Screen_Shot_2021-03-18_at_2.23.56_PM.jpeg",
      "description": "OMG incredibly delicious katsu sandwich! Chicken katsu is my fave but they're all good! The bread is like a pillow.",
      "likes": 5,
      "user": "Leah",
      "id": 3
    },
    {
      "name": "Clockwork Bar",
      "borough": "Manhattan",
      "area": "Lower East Side",
      "category": "🍸",
      "url": "https://www.clockworknyc.com/",
      "img": "https://s3.amazonaws.com/nooklyn-pro/locationphotos/4118/standard/Clockwork_Bar-6.jpg?1529337974",
      "description": "Divey yet iconic punk bar! Great place to meet up with friends. You will not get in trouble for adding graffiti.",
      "likes": 3,
      "user": "Leah",
      "id": 4
    },
    {
      "name": "Poster House",
      "borough": "Manhattan",
      "area": "Chelsea",
      "category": "🎨",
      "url": "https://posterhouse.org/",
      "img": "https://static01.nyt.com/images/2019/06/28/arts/28POSTERS01/28POSTERS01-superJumbo-v2.jpg",
      "description": "Cheap museum (+ free admission on Fridays!) with rotating exhibits of stunning vintage and modern posters from around the world.",
      "likes": 2,
      "user": "Leah",
      "id": 5
    },
    {
      "name": "Madison Square Garden",
      "borough": "Manhattan",
      "area": "Herald Square",
      "category": "🎶",
      "url": "https://www.msg.com/madison-square-garden",
      "img": "https://smedia.pnet-static.com/img/MSG1731.jpg_large",
      "description": "MSG is the 'World's Most Famous Arena' and for good reason. Besides being the home of the NY Knicks & Rangers, it is the premier venue to see world-class musicians perform. In fact, Phish has played here 81 times since 1994!",
      "likes": 11,
      "user": "Leah",
      "id": 6
    },
    {
      "name": "Transmitter Park Mural",
      "borough": "Brooklyn",
      "area": "Greenpoint",
      "category": "🎨",
      "url": "https://www.nycgovparks.org/parks/transmitter-park",
      "img": "https://live.staticflickr.com/65535/48105283341_555646e8a4_b.jpg",
      "description": "My favorite mural in all of NYC. It lives in Transmitter Park-- a small, peaceful park with stunning views of Manhattan.",
      "likes": 6,
      "user": "Leah",
      "id": 7
    },
    {
      "name": "Ops",
      "borough": "Brooklyn",
      "area": "Bushwick",
      "category": "🌭",
      "url": "http://www.opsbk.com/",
      "img": "https://infatuation.imgix.net/media/images/reviews/ops/Ops%20-%20Square%20Pie.jpg",
      "description": "My favorite pizza place in all of NYC. It's a sit-down restaurant so expect to pay more than you would at a slice shop, but it will be well worth it. They also have an amazing wine program, just tell them what you like and they will bring you some options to taste!",
      "likes": 10,
      "user": "Leah",
      "id": 8
    },
    {
      "name": "Mad Tropical",
      "borough": "Brooklyn",
      "area": "Bushwick",
      "category": "🍸",
      "url": "https://www.madtropical.com/",
      "img": "https://images.squarespace-cdn.com/content/v1/5951a2eee6f2e17c04d34f16/1498572951008-MRW2PM85XKMQ6SIC3QFX/KN0A6636.jpg",
      "description": "Many vibes to this place-- a tropical bar in the front, a casual lounge in the middle, and a disco dancefloor in the back- complete with a DJ spinning strictly 70s and 80s vinyl (bangers only). Watch out for the passionfruit margaritas... they're delicious but dangerous!",
      "likes": 6,
      "user": "Leah",
      "id": 9
    },
    {
      "name": "Felix Roasting Co.",
      "borough": "Manhattan",
      "area": "Nomad",
      "category": "☕️",
      "url": "https://felixroastingco.com/",
      "img": "https://media.timeout.com/images/105325738/image.jpg",
      "description": "Out of this world coffee and stunning interiors. If you want to go big, get the hickory-smoked s'mores latte with homemade roasted marshmallow.",
      "likes": 7,
      "user": "Leah",
      "id": 10
    },
    {
      "name": "Yemen Cafe",
      "borough": "Brooklyn",
      "area": "Cobble Hill",
      "category": "🌭",
      "url": "https://www.yemencafe.com/",
      "img": "https://img.cdn4dd.com/cdn-cgi/image/fit=contain,width=1200,height=672,format=auto/https://doordash-static.s3.amazonaws.com/media/store/header/215616.jpg",
      "description": "Best meal under $20... If you've never tried Yemeni cuisine before, this is the spot to go to! Plus, there's unlimited bread, soup, and tea.",
      "likes": 5,
      "user": "Leah",
      "id": 11
    },
    {
      "name": "Kings Theatre",
      "borough": "Brooklyn",
      "area": "Flatbush",
      "category": "🎶",
      "url": "https://www.kingstheatre.com/?utm_source=google&utm_medium=organic&utm_campaign=gmb",
      "img": "https://www.kingstheatre.com/media/ysgnnj14/kings-venue-2-1920x1280.jpg",
      "description": "Gorgeous theatre right next to Prospect Park. It has been around since 1929 and every concert I've seen here has been spectacular.",
      "likes": 4,
      "user": "Leah",
      "id": 12
    },
    {
      "name": "Fotografiska",
      "borough": "Brooklyn",
      "area": "Gramercy Park",
      "category": "🎨",
      "url": "https://www.fotografiska.com/nyc/",
      "img": "https://dynamic-media-cdn.tripadvisor.com/media/photo-o/1b/f5/f6/91/caption.jpg?w=1200&h=-1&s=1",
      "description": "A must-see if you're a photography lover!",
      "user": "Leah",
      "id": 13,
      "likes": 1
    },
    {
      "name": "McSorley’s Old Ale House",
      "borough": "Manhattan",
      "area": "Noho",
      "category": "🍸",
      "url": "https://mcsorleysoldalehouse.nyc/",
      "img": "https://imgs.6sqft.com/wp-content/uploads/2017/03/10104443/02McSorleysInterior5Center72900.jpg",
      "description": "Old school Irish pub established in 1854! It only serves two drinks: light beer and dark beer.",
      "likes": 4,
      "user": "Leah",
      "id": 14
    },
    {
      "name": "The Hideout Chai Bar",
      "borough": "Manhattan",
      "area": "Bowery",
      "category": "☕️",
      "url": "https://www.thehideoutnyc.com/",
      "img": "https://fastly.4sqi.net/img/general/600x600/42602567_eLQ5JgTfxRmdV7FKnmah2IiAGoM6RAGPh7t8hqe9xe4.jpg",
      "description": "Minimalist, authentic tiny chai shop!",
      "likes": 2,
      "user": "Leah",
      "id": 15
    },
    {
      "name": "Win Son Bakery",
      "borough": "Brooklyn",
      "area": "Williamsburg",
      "category": "🌭",
      "url": "https://winsonbrooklyn.com/bakery",
      "img": "https://img.cdn4dd.com/cdn-cgi/image/fit=contain,width=1200,height=672,format=auto/https://doordash-static.s3.amazonaws.com/media/photosV2/5fdaf17d-aa24-497d-9681-66fc804acca4-retina-large.PNG",
      "description": "Your new favorite brunch spot. Get the scallion pancake BEC, fan tuan (rice roll stuffed with crispy pork), and mochi donut!",
      "likes": 8,
      "user": "Leah",
      "id": 16
    },
    {
      "name": "Smalls Jazz Club",
      "borough": "Manhattan",
      "area": "West Village",
      "category": "🎶",
      "url": "https://www.smallslive.com/",
      "img": "https://assets3.thrillist.com/v1/image/1679163/1200x630",
      "description": "Iconic NYC basement jazz club!",
      "likes": 8,
      "user": "Leah",
      "id": 17
    },
    {
      "name": "Whitney Museum",
      "borough": "Manhattan",
      "area": "Chelsea",
      "category": "🎨",
      "url": "https://whitney.org/",
      "img": "https://whitneymedia.org/assets/image/800530/large_square-36-978a7525.jpg",
      "description": "Fascinating American contemporary art museum!",
      "likes": 2,
      "user": "Leah",
      "id": 18
    },
    {
      "name": "The Flower Shop",
      "borough": "Manhattan",
      "area": "Bowery",
      "category": "🍸",
      "url": "https://www.theflowershopnyc.com/",
      "img": "https://images.otstatic.com/prod/26315657/3/huge.jpg",
      "description": "Lowkey, classy bar with an upstairs and downstairs bar. There's a pool table in the basement and on Wednesday nights they do an awesome trivia night down there!",
      "likes": 3,
      "user": "Leah",
      "id": 19
    },
    {
      "name": "Variety Coffee Roasters",
      "borough": "Brooklyn",
      "area": "Williamsburg",
      "category": "☕️",
      "url": "https://varietycoffeeroasters.com/",
      "img": "https://cdn.shopify.com/s/files/1/0015/7846/7428/files/image_27_55afe700-70d8-4b67-bb5c-d1f6fad6a410.jpg?v=1639436103&width=550",
      "description": "Reliable neighborhood coffee shop! Fast, fresh, and delicious.",
      "likes": 1,
      "user": "Leah",
      "id": 20
    }
  ]
}